{
  "date": "2026/07/07",
  "facility": "honmoku",
  "weather": "曇り時々晴れ",
  "water_temp": 23.5,
  "tide": "小潮",
  "visitors": 279,
  "comment": "本日は本牧海づり施設にご来場いただきありがとうございます。\n\n朝と午後に少し雨が降りましたが、時折日差しもあり釣り日和となりました。\n\nサビキ釣りではアジ、サッパが好調でした。アジは沖桟橋の一部で9時から10時まで時合があったようです。また新旧護岸でも足元で釣れていました。\n投げ釣りのシロギスは一休みといったところでしょうか。新護岸では今日もイシモチの大物賞が出ています。\n\n明日は一日を通して晴れ、最高気温は30度近くまで上がる予報です。紫外線対策、熱中症対策をしっかりしてお越し下さい。\n\nスタッフ一同皆様のご来場をお待ちしております。\n\n※2025年4月1日から横浜市港湾施設条例施行規則の改定により、釣り場と駐車場が禁煙となりました。\nタバコは加熱式も含め、新護岸スロープ下の喫煙所でお願い致します。\n\n※『釣果情報』につきましては、お客様のお帰り時の聞き取り調査の集計となります。\n尚、小さな個体は釣果数にカウントしない場合がございます。\n小さな魚はなるべく元気な内にリリースして頂けます様、ご協力をお願い致します。\n",
  "catches": []
}