{
  "date": "2026/06/25",
  "facility": "honmoku",
  "weather": "雨",
  "water_temp": 23,
  "tide": "若潮",
  "visitors": 88,
  "comment": "本日は本牧海づり施設にご来場いただきまして、誠にありがとうございます。\n一日雨とタフなコンディションとなりました。\n\nサビキ釣りのアジはポツポツ釣れ続け、多い方で51匹でした。渡桟橋ではカサゴが数が出ました。またメバルの良型も顔を見せています。\n\n明日は曇り時々雨、台風の影響で南西の風が大変強く吹く予報です。しっかりとした雨具をご準備の上、体温調節のできる服装でお越しください。事前に天気予報をご確認いただきますようお願いします。\n\n断続的な風速15メートル確認しますと沖桟橋は閉鎖します。風速が20メートルとなりますと釣り場を全面閉鎖します。予めご了承ください。\n\n【濱ともカードご優待日】\n毎週金曜日は「濱ともカード」がご利用出来ます。濱ともカード対象の方は、濱ともカード入場券をご購入の上、受付でご提示下さい。当日の釣り料金が半額でご利用頂けます。\n\n\n※『釣果情報』につきましては、お客様のお帰り時の聞き取り調査の集計です。\n尚、小さな個体は釣果数にカウントしない場合がございます。\n小さな魚はなるべく元気な内にリリースして頂けます様、ご協力をお願い致します。",
  "catches": []
}